pypomes_jwt/__init__.py
pypomes_jwt/jwt_config.py
pypomes_jwt/jwt_pomes.py
pypomes_jwt/jwt_registry.py
pypomes_jwt-1.4.4.dist-info/METADATA
pypomes_jwt-1.4.4.dist-info/WHEEL
pypomes_jwt-1.4.4.dist-info/licenses/LICENSE
pypomes_jwt-1.4.4.dist-info/RECORD
