Metadata-Version: 2.4
Name: pypomes_jwt
Version: 1.4.4
Summary: A collection of Python pomes, penyeach (JWT module)
Project-URL: Homepage, https://github.com/TheWiseCoder/PyPomes-JWT
Project-URL: Bug Tracker, https://github.com/TheWiseCoder/PyPomes-JWT/issues
Author-email: GT Nunes <wisecoder01@gmail.com>
License-File: LICENSE
Classifier: License :: OSI Approved :: MIT License
Classifier: Operating System :: OS Independent
Classifier: Programming Language :: Python :: 3
Requires-Python: >=3.14
Requires-Dist: cryptography>=46.0.3
Requires-Dist: flask>=3.1.2
Requires-Dist: pyjwt>=2.10.1
Requires-Dist: pypomes-core>=3.0.8
Requires-Dist: pypomes-crypto>=0.8.7
Requires-Dist: pypomes-db>=2.8.7
